AUTHORS.TXT
CHANGES.txt
README.txt
bootstrap.py
buildout.cfg
setup.py
src/enfold/__init__.py
src/enfold.gcache.egg-info/PKG-INFO
src/enfold.gcache.egg-info/SOURCES.txt
src/enfold.gcache.egg-info/dependency_links.txt
src/enfold.gcache.egg-info/namespace_packages.txt
src/enfold.gcache.egg-info/not-zip-safe
src/enfold.gcache.egg-info/requires.txt
src/enfold.gcache.egg-info/top_level.txt
src/enfold/gcache/__init__.py
src/enfold/gcache/cache.py
src/enfold/gcache/diskstorage.py
src/enfold/gcache/httpcache.py
src/enfold/gcache/httpcacheprovider.py
src/enfold/gcache/interfaces.py
src/enfold/gcache/priqueue.py
src/enfold/gcache/stats.py
src/enfold/gcache/utils.py
src/enfold/gcache/examples/caching_http_proxy.py
src/enfold/gcache/tests/__init__.py
src/enfold/gcache/tests/hammer_gcache.py
src/enfold/gcache/tests/scale.py
src/enfold/gcache/tests/test.py
src/enfold/gcache/tests/testHTTPCache.py
src/enfold/gcache/tests/testHTTPProvider.py
src/enfold/gcache/tests/testRFC2616.py