Metadata-Version: 1.0
Name: enfold.gcache
Version: 2.0.1
Summary: Simple pluggable caching server.
Home-page: http://www.enfoldsystems.com
Author: Enfold Systems
Author-email: info@enfoldsystems.com
License: LGPL
Keywords: cache caching
Platform: UNKNOWN
Classifier: Development Status :: 5 - Production/Stable
Classifier: Intended Audience :: Developers
Classifier: License :: OSI Approved :: GNU Library or Lesser General Public License (LGPL)
Classifier: Operating System :: OS Independent
Classifier: Programming Language :: Python
